trashdetect_engine/__init__.py
trashdetect_engine/coco_eval.py
trashdetect_engine/data.py
trashdetect_engine/engine.py
trashdetect_engine/transforms.py
trashdetect_engine/utils.py
trashdetect_engine/models/__init__.py
trashdetect_engine/models/segmentation_models.py
trashdetect_engine-0.1.1.dist-info/METADATA
trashdetect_engine-0.1.1.dist-info/WHEEL
trashdetect_engine-0.1.1.dist-info/top_level.txt
trashdetect_engine-0.1.1.dist-info/zip-safe
trashdetect_engine-0.1.1.dist-info/RECORD
