Metadata-Version: 2.1
Name: trashdetect-engine
Version: 0.1.1
Summary: trashdetect_engine
Home-page: UNKNOWN
Author: NMA2022DL_TrashDetect_Team
License: MIT
Platform: UNKNOWN
Classifier: Programming Language :: Python :: 3
Classifier: License :: OSI Approved :: MIT License
Classifier: Operating System :: OS Independent
Classifier: Topic :: Scientific/Engineering :: Artificial Intelligence
